{
  "inserts": [
    { "code": "01R2101", "size": "CR05", "parts_no": "R06005-05006-32", "coating": "TiAlN", "grade": "K20F", "d": 5, "d1": 3.9, "l": 0.06, "s": 2, "pitch_min": 0.6, "pitch_max": 0.75, "thread_angle": "60°" },
    { "code": "01R2102", "size": "CR05", "parts_no": "R06005-05006-00", "coating": "Uncoated", "grade": "K20F", "d": 5, "d1": 3.9, "l": 0.06, "s": 2, "pitch_min": 0.6, "pitch_max": 0.75, "thread_angle": "60°" },
    { "code": "01R2103", "size": "CR05", "parts_no": "R06005-05010-32", "coating": "TiAlN", "grade": "K20F", "d": 5, "d1": 3.9, "l": 0.1, "s": 2, "pitch_min": 0.8, "pitch_max": 1, "thread_angle": "60°" },
    { "code": "01R2104", "size": "CR05", "parts_no": "R06005-05010-00", "coating": "Uncoated", "grade": "K20F", "d": 5, "d1": 3.9, "l": 0.1, "s": 2, "pitch_min": 0.8, "pitch_max": 1, "thread_angle": "60°" },
    { "code": "01R2301", "size": "CR07", "parts_no": "R06007-06810-32", "coating": "TiAlN", "grade": "K20F", "d": 6.8, "d1": 5.5, "l": 0.1, "s": 2.35, "pitch_min": 0.8, "pitch_max": 1.25, "thread_angle": "60°" },
    { "code": "01R2302", "size": "CR07", "parts_no": "R06007-06810-00", "coating": "Uncoated", "grade": "K20F", "d": 6.8, "d1": 5.5, "l": 0.1, "s": 2.35, "pitch_min": 0.8, "pitch_max": 1.25, "thread_angle": "60°" },
    { "code": "01R2601", "size": "CR10", "parts_no": "R06010-08510-32", "coating": "TiAlN", "grade": "K20F", "d": 8.5, "d1": 6.9, "l": 0.1, "s": 3.6, "pitch_min": 1, "pitch_max": 1.5, "thread_angle": "60°" },
    { "code": "01R2602", "size": "CR10", "parts_no": "R06010-08510-00", "coating": "Uncoated", "grade": "K20F", "d": 8.5, "d1": 6.9, "l": 0.1, "s": 3.6, "pitch_min": 1, "pitch_max": 1.5, "thread_angle": "60°" },
    { "code": "01R2603", "size": "CR10", "parts_no": "R06010-10010-32", "coating": "TiAlN", "grade": "K20F", "d": 10, "d1": 6.9, "l": 0.1, "s": 3.6, "pitch_min": 1, "pitch_max": 2, "thread_angle": "60°" },
    { "code": "01R2604", "size": "CR10", "parts_no": "R06010-10010-00", "coating": "Uncoated", "grade": "K20F", "d": 10, "d1": 6.9, "l": 0.1, "s": 3.6, "pitch_min": 1, "pitch_max": 2, "thread_angle": "60°" }
  ],
  "holders": [
    { "code": "70R104", "size": "CR05", "parts_no": "00-99626-CR05-06-039", "type": "BC06-CR05-039", "shank": "Steel", "d": 6, "l": 39, "screw": "NS-20045" },
    { "code": "70R105", "size": "CR05", "parts_no": "00-99626-CR05-06-045", "type": "BC06-CR05-045", "shank": "Steel", "d": 6, "l": 45, "screw": "NS-20045" },
    { "code": "70R103", "size": "CR05", "parts_no": "00-99626-CR05-08-076", "type": "BC08-CR05-076", "shank": "Steel", "d": 8, "l": 74, "screw": "NS-20045" },
    { "code": "70R101", "size": "CR05", "parts_no": "00-99626-CR05-05-043", "type": "BC05-CR05-043", "shank": "Steel", "d": 5, "l": 41, "screw": "NS-20045" },
    { "code": "70R106", "size": "CR05", "parts_no": "00-99626-CR05-06-051", "type": "BC06-CR05-051", "shank": "Steel", "d": 6, "l": 51, "screw": "NS-20045" },
    { "code": "70R107", "size": "CR05", "parts_no": "00-99626-CR05-06-051W", "type": "BC06-CR05-051W", "shank": "Carbide", "d": 6, "l": 51, "screw": "NS-20045" },
    { "code": "70R201", "size": "CR06", "parts_no": "00-99626-CR06-06-041", "type": "BC06-CR06-041", "shank": "Steel", "d": 6, "l": 41, "screw": "NS-22062" },
    { "code": "70R202", "size": "CR06", "parts_no": "00-99626-CR06-06-047", "type": "BC06-CR06-047", "shank": "Steel", "d": 6, "l": 47, "screw": "NS-22062" },
    { "code": "70R203", "size": "CR06", "parts_no": "00-99626-CR06-06-053", "type": "BC06-CR06-053", "shank": "Steel", "d": 6, "l": 53, "screw": "NS-22062" },
    { "code": "70R204", "size": "CR06", "parts_no": "00-99626-CR06-06-053W", "type": "BC06-CR06-053W", "shank": "Carbide", "d": 6, "l": 53, "screw": "NS-22062" },
    { "code": "70R304", "size": "CR07", "parts_no": "00-99626-CR07-06-041", "type": "BC06-CR07-041", "shank": "Steel", "d": 6, "l": 41, "screw": "NS-25060" },
    { "code": "70R303", "size": "CR07", "parts_no": "00-99626-CR07-08-078", "type": "BC08-CR07-078", "shank": "Steel", "d": 8, "l": 75, "screw": "NS-25060" },
    { "code": "70R305", "size": "CR07", "parts_no": "00-99626-CR07-06-049", "type": "BC06-CR07-049", "shank": "Steel", "d": 6, "l": 49, "screw": "NS-25060" },
    { "code": "70R301", "size": "CR07", "parts_no": "00-99626-CR07-06-052", "type": "BC06-CR07-052", "shank": "Steel", "d": 6, "l": 49, "screw": "NS-25060" },
    { "code": "70R306", "size": "CR07", "parts_no": "00-99626-CR07-06-057", "type": "BC06-CR07-057", "shank": "Steel", "d": 6, "l": 57, "screw": "NS-25060" },
    { "code": "70R307", "size": "CR07", "parts_no": "00-99626-CR07-06-057W", "type": "BC06-CR07-057W", "shank": "Carbide", "d": 6, "l": 57, "screw": "NS-25060" },
    { "code": "70R604", "size": "CR10", "parts_no": "00-99626-CR10-08-049", "type": "BC08-CR10-049", "shank": "Steel", "d": 8, "l": 49, "screw": "NS-35080" },
    { "code": "70R603", "size": "CR10", "parts_no": "00-99626-CR10-08-082", "type": "BC08-CR10-082", "shank": "Steel", "d": 8, "l": 78, "screw": "NS-35080" },
    { "code": "70R605", "size": "CR10", "parts_no": "00-99626-CR10-08-059", "type": "BC08-CR10-059", "shank": "Steel", "d": 8, "l": 59, "screw": "NS-35080" },
    { "code": "70R606", "size": "CR10", "parts_no": "00-99626-CR10-08-069", "type": "BC08-CR10-069", "shank": "Steel", "d": 8, "l": 69, "screw": "NS-35080" },
    { "code": "70R607", "size": "CR10", "parts_no": "00-99626-CR10-08-084W", "type": "BC08-CR10-084W", "shank": "Carbide", "d": 8, "l": 84, "screw": "NS-35080" }
  ]
}